<!--
SPDX-FileCopyrightText: 2025 Aiden <28298836+Aidenkrz@users.noreply.github.com>
SPDX-FileCopyrightText: 2025 ArtisticRoomba <145879011+ArtisticRoomba@users.noreply.github.com>

SPDX-License-Identifier: AGPL-3.0-or-later
-->

<Document>
  # Surveillance et contrôle des appareils
  Étant donné la portée à l'échelle de la station du réseau atmosphérique, il est important de disposer d'un moyen de surveiller et de contrôler les appareils depuis un emplacement central.

  Grâce à ces systèmes, le service Atmosphérique peut surveiller et contrôler l'atmosphère de toute la station.

  <Box>
    <GuideEntityEmbed Entity="AirAlarm" Caption=""/>
    <GuideEntityEmbed Entity="AirSensor" Caption=""/>
  </Box>
  <Box>
    ## Alarmes atmosphériques
  </Box>
  <Box>
    [color=#999999][italic]Surveillance et contrôle à grande portée des appareils atmosphériques[italic][/color]
  </Box>

  <Box>
    <GuideEntityEmbed Entity="ComputerAlert" Caption=""/>
  </Box>
  <Box>
    ## Ordinateur d'alertes atmosphériques
  </Box>
  <Box>
    [color=#999999][italic]Surveillance à l'échelle de la station des alarmes atmosphériques[italic][/color]
  </Box>

  <Box>
    <GuideEntityEmbed Entity="ComputerAtmosMonitoring" Caption=""/>
    <GuideEntityEmbed Entity="GasPipeSensor" Caption=""/>
  </Box>
  <Box>
    ## Moniteur de réseau atmosphérique
  </Box>
  <Box>
    [color=#999999][italic]Surveillance des réseaux de tuyaux complets[italic][/color]
  </Box>

</Document>
